[
  {
    "id": 1,
    "item": "Civic",
    "isMultipricing": true
  },
  {
    "id": 2,
    "item": "Prius",
    "isMultipricing": false
  },
  {
    "id": 3,
    "item": "Z4 M",
    "isMultipricing": true
  },
  {
    "id": 4,
    "item": "Jimmy",
    "isMultipricing": true
  },
  {
    "id": 5,
    "item": "Edge",
    "isMultipricing": true
  },
  {
    "id": 6,
    "item": "200",
    "isMultipricing": false
  },
  {
    "id": 7,
    "item": "Lancer",
    "isMultipricing": true
  },
  {
    "id": 8,
    "item": "62",
    "isMultipricing": true
  },
  {
    "id": 9,
    "item": "Sephia",
    "isMultipricing": false
  },
  {
    "id": 10,
    "item": "Cutlass Supreme",
    "isMultipricing": true
  },
  {
    "id": 11,
    "item": "Somerset",
    "isMultipricing": false
  },
  {
    "id": 12,
    "item": "Expedition",
    "isMultipricing": true
  },
  {
    "id": 13,
    "item": "Freelander",
    "isMultipricing": false
  },
  {
    "id": 14,
    "item": "Express 2500",
    "isMultipricing": true
  },
  {
    "id": 15,
    "item": "Tribute",
    "isMultipricing": false
  }
]